graphcol/__init__.py
graphcol/exatos.py
graphcol/gulosos.py
graphcol/metaheuristicas.py
graphcol/visual.py
graphcol-0.4.2.dist-info/WHEEL
graphcol-0.4.2.dist-info/METADATA
graphcol-0.4.2.dist-info/RECORD
