Metadata-Version: 2.1
Name: graphcol
Version: 0.4.2
Summary: 
Author: WLAraujo
Author-email: lima.wesleyaraujo@gmail.com
Requires-Python: >=3.8,<4.0
Classifier: Programming Language :: Python :: 3
Classifier: Programming Language :: Python :: 3.8
Classifier: Programming Language :: Python :: 3.9
Classifier: Programming Language :: Python :: 3.10
Classifier: Programming Language :: Python :: 3.11
Requires-Dist: cairocffi (>=1.3.0,<2.0.0)
Requires-Dist: igraph (>=0.9.9,<0.10.0)
Requires-Dist: matplotlib (>=3.6.0,<4.0.0)
Requires-Dist: numpy (>=1.23.0,<2.0.0)
